tonio-0.1.0a4.dist-info/METADATA
tonio-0.1.0a4.dist-info/WHEEL
tonio-0.1.0a4.dist-info/licenses/LICENSE
tonio/__init__.py
tonio/_colored/__init__.py
tonio/_colored/_ctl.py
tonio/_colored/_net/__init__.py
tonio/_colored/_net/_socket.py
tonio/_colored/_scope.py
tonio/_colored/_sync.py
tonio/_colored/_time.py
tonio/_ctl.py
tonio/_deco.py
tonio/_events.py
tonio/_net/__init__.py
tonio/_net/_socket.py
tonio/_runtime.py
tonio/_scope.py
tonio/_sync.py
tonio/_time.py
tonio/_tonio.cpython-314t-aarch64-linux-gnu.so
tonio/_tonio.pyi
tonio/_types.py
tonio/_utils.py
tonio/colored/__init__.py
tonio/colored/net/__init__.py
tonio/colored/net/socket.py
tonio/colored/sync/__init__.py
tonio/colored/sync/channel/__init__.py
tonio/colored/time.py
tonio/exceptions.py
tonio/net/__init__.py
tonio/net/socket.py
tonio/sync/__init__.py
tonio/sync/channel/__init__.py
tonio/time.py
tonio-0.1.0a4.dist-info/RECORD
