Metadata-Version: 2.4
Name: tonio
Version: 0.1.0a4
Classifier: Development Status :: 3 - Alpha
Classifier: Intended Audience :: Developers
Classifier: License :: OSI Approved :: BSD License
Classifier: Operating System :: MacOS
Classifier: Operating System :: POSIX :: Linux
Classifier: Programming Language :: Python :: Free Threading :: 2 - Beta
Classifier: Programming Language :: Python :: 3
Classifier: Programming Language :: Python :: 3.14
Classifier: Programming Language :: Python :: Implementation :: CPython
Classifier: Programming Language :: Python
Classifier: Programming Language :: Rust
License-File: LICENSE
Summary: A multi-threaded async runtime
Keywords: async,io,threading,networking
Home-Page: https://github.com/gi0baro/tonio
Author-email: Giovanni Barillari <g@baro.dev>
License: BSD-3-Clause
Requires-Python: >=3.14
Project-URL: Homepage, https://github.com/gi0baro/tonio
Project-URL: Funding, https://github.com/sponsors/gi0baro
Project-URL: Source, https://github.com/gi0baro/tonio
